octohatrack/__init__.py
octohatrack/__main__.py
octohatrack/_version.py
octohatrack/api_helpers.py
octohatrack/code_contrib.py
octohatrack/contributors_file.py
octohatrack/helpers.py
octohatrack/wiki.py
octohatrack-1.1.0.dist-info/LICENSE
octohatrack-1.1.0.dist-info/METADATA
octohatrack-1.1.0.dist-info/WHEEL
octohatrack-1.1.0.dist-info/entry_points.txt
octohatrack-1.1.0.dist-info/top_level.txt
octohatrack-1.1.0.dist-info/RECORD
