Metadata-Version: 2.1
Name: octohatrack
Version: 1.1.0
Summary: Show _all_ the contributors to a GitHub repository
Home-page: https://github.com/labhr/octohatrack
Author: Katie McLaughlin
Author-email: katie@glasnt.com
License: MIT
Keywords: octohatrack github contributions
Platform: UNKNOWN
Classifier: License :: OSI Approved :: MIT License
Classifier: Programming Language :: Python :: 3
Requires-Dist: requests
Requires-Dist: gitpython
Requires-Dist: requests-cache
